broken2merge/__init__.py
broken2merge/__main__.py
broken2merge/alignment.py
broken2merge/cli.py
broken2merge/utils.py
broken2merge-0.3.0.dist-info/LICENSE
broken2merge-0.3.0.dist-info/METADATA
broken2merge-0.3.0.dist-info/WHEEL
broken2merge-0.3.0.dist-info/entry_points.txt
broken2merge-0.3.0.dist-info/RECORD
