Metadata-Version: 2.1
Name: broken2merge
Version: 0.3.0
Summary: Tool to merge broken gene due to assembly error based on the alignment
Home-page: https://github.com/rdenise/broken_merge
License: MIT
Author: Remi Denise
Requires-Python: >=3.9,<3.13
Classifier: Development Status :: 5 - Production/Stable
Classifier: Environment :: Console
Classifier: Intended Audience :: Science/Research
Classifier: License :: OSI Approved :: MIT License
Classifier: Operating System :: POSIX
Classifier: Programming Language :: Python :: 3
Classifier: Programming Language :: Python :: 3.9
Classifier: Programming Language :: Python :: 3.10
Classifier: Programming Language :: Python :: 3.11
Classifier: Programming Language :: Python :: 3.12
Requires-Dist: biopython (>=1.81,<2.0)
Requires-Dist: numpy (>=1.26.0,<2.0.0)
Requires-Dist: tqdm (>=4.66.1,<5.0.0)
Project-URL: Bug Tracker, https://github.com/rdenise/broken_merge/issues
Project-URL: Repository, https://github.com/rdenise/broken_merge
